{
    "description": "This file records version numbers for each SdkGenerator target.  Keys must be lowercase, and match subfolders in SdkGenerator/targets.",
    "sdkVersion": {
        "azure": "0.97.251024",
        "csharp": "1.211.251024",
        "javascript": "1.202.251024",
        "java": "0.247.251024",
        "luasdk": "0.214.251024",
        "js-node": "2.184.251024",
        "postman": "0.239.251024",
        "unity-v2": "2.224.251024",
        "xplatcppsdk": "3.167.251024",
        "phpsdk": "0.0.251024",
        "sdktestingcloudscript": "0.0.251024",
        "objc": "0.0.251024",
        "pythonsdk": "0.0.251024",
        "unrealmarketplaceplugin": "1.174.251024",
        "newtarget": "0.0.todaysDate",
        "jcutestrepo": "0.0.251024"
    }
}