{
    "description": "This file records version numbers for each SdkGenerator target.  Keys must be lowercase, and match subfolders in SdkGenerator/targets.",
    "sdkVersion": {
        "actionscript": "0.105.200518",
        "cpp-cocos2dx": "0.83.200518",
        "csharp": "1.72.200518",
        "javascript": "1.65.200518",
        "java": "0.110.200518",
        "luasdk": "0.77.200518",
        "js-node": "2.47.200518",
        "postman": "0.101.200518",
        "unity-v2": "2.86.200518",
        "xplatcppsdk": "3.29.200518",
        "phpsdk": "0.0.200518",
        "sdktestingcloudscript": "0.0.200518",
        "objc": "0.0.200518",
        "pythonsdk": "0.0.200518",
        "unrealmarketplaceplugin": "1.37.200518",
        "newtarget": "0.0.todaysDate",
        "jcutestrepo": "0.0.1"
    }
}