{
    "description": "This file records version numbers for each SdkGenerator target.  Keys must be lowercase, and match subfolders in SdkGenerator/targets.",
    "sdkVersion": {
        "csharp": "1.105.211108",
        "javascript": "1.96.211108",
        "java": "0.141.211108",
        "luasdk": "0.108.211108",
        "js-node": "2.78.211108",
        "postman": "0.133.211108",
        "unity-v2": "2.118.211108",
        "xplatcppsdk": "3.61.211108",
        "phpsdk": "0.0.211108",
        "sdktestingcloudscript": "0.0.211108",
        "objc": "0.0.211108",
        "pythonsdk": "0.0.211108",
        "unrealmarketplaceplugin": "1.68.211108",
        "newtarget": "0.0.todaysDate",
        "jcutestrepo": "0.0.211108"
    }
}