{
    "description": "This file records version numbers for each SdkGenerator target.  Keys must be lowercase, and match subfolders in SdkGenerator/targets.",
    "sdkVersion": {
        "azure": "0.15.220802",
        "csharp": "1.129.220802",
        "javascript": "1.120.220802",
        "java": "0.165.220802",
        "luasdk": "0.132.220802",
        "js-node": "2.102.220802",
        "postman": "0.157.220802",
        "unity-v2": "2.142.220802",
        "xplatcppsdk": "3.85.220802",
        "phpsdk": "0.0.220802",
        "sdktestingcloudscript": "0.0.220802",
        "objc": "0.0.220802",
        "pythonsdk": "0.0.220802",
        "unrealmarketplaceplugin": "1.92.220802",
        "newtarget": "0.0.todaysDate",
        "jcutestrepo": "0.0.220802"
    }
}